data_process/get_data/__init__.py
data_process/get_data/source_databank.py
data_process/get_data/source_email.py
data_process/get_data/source_file.py
data_process/model_process/__init__.py
data_process/model_process/data_process.py
data_process/model_process/sklearn_process.py
dm_data_process-0.0.4.dist-info/DESCRIPTION.rst
dm_data_process-0.0.4.dist-info/METADATA
dm_data_process-0.0.4.dist-info/RECORD
dm_data_process-0.0.4.dist-info/WHEEL
dm_data_process-0.0.4.dist-info/metadata.json
dm_data_process-0.0.4.dist-info/top_level.txt
