Metadata-Version: 2.0
Name: dm-data-process
Version: 0.0.4
Summary: This is a sample package
Home-page: UNKNOWN
Author: Damon
Author-email: 5178646@qq.com
License: MIT
Platform: UNKNOWN
